interpret.py
summarize.py
ai2op-0.5.dist-info/METADATA
ai2op-0.5.dist-info/WHEEL
ai2op-0.5.dist-info/top_level.txt
ai2op-0.5.dist-info/RECORD
