Metadata-Version: 2.1
Name: ai2op
Version: 0.5
Summary: A package for fine-tuning and utilizing the ai2op model
Home-page: https://github.com/sscla1/ai2op
Author: Collin Lafayette
Author-email: sscla-ops@outlook.com
Keywords: machine-learning transformers fine-tuning ai market data stock option trading automation
Classifier: Development Status :: 3 - Alpha
Classifier: Intended Audience :: Developers
Classifier: License :: OSI Approved :: MIT License
Classifier: Programming Language :: Python :: 3
Classifier: Programming Language :: Python :: 3.6
Classifier: Programming Language :: Python :: 3.7
Classifier: Programming Language :: Python :: 3.8
Classifier: Programming Language :: Python :: 3.9
Requires-Dist: torch
Requires-Dist: transformers
Requires-Dist: pandas
Requires-Dist: nbformat
Requires-Dist: chardet
